util_helper/__init__.py
util_helper/compare_strings.py
util_helper/file_handler.py
util_helper/text_preprocessor.py
util_helper-0.0.5.dist-info/METADATA
util_helper-0.0.5.dist-info/WHEEL
util_helper-0.0.5.dist-info/top_level.txt
util_helper-0.0.5.dist-info/RECORD
